{"namedChunkGroups":{"polyfill":{"name":"polyfill","assets":[{"name":"webpack-runtime-d883e5a693f658cfd86d.js","size":6526},{"name":"commons-8a6a7fb433791e1b3b36.js","size":836594},{"name":"polyfill-b792846b84be83ff28ed.js","size":83608}],"filteredAssets":0,"assetsSize":926728,"filteredAuxiliaryAssets":5,"auxiliaryAssetsSize":4188182},"app":{"name":"app","assets":[{"name":"webpack-runtime-d883e5a693f658cfd86d.js","size":6526},{"name":"styles.0f615b844f73f4ec7f93.css","size":57346},{"name":"framework-3a2d1079ef1a8666f37a.js","size":129887},{"name":"app-6555c2e857f6df37dde5.js","size":185576}],"filteredAssets":0,"assetsSize":379335,"filteredAuxiliaryAssets":75,"auxiliaryAssetsSize":2307525},"component---src-pages-404-js":{"name":"component---src-pages-404-js","assets":[{"name":"styles.0f615b844f73f4ec7f93.css","size":57346},{"name":"c16184b3-019e6a7e87c7a4de7da9.js","size":8424},{"name":"2cca2479-62bb829e6f32669238be.js","size":3393},{"name":"b637e9a5-7c7096449bf2c50c0059.js","size":87228},{"name":"commons-8a6a7fb433791e1b3b36.js","size":836594},{"name":"component---src-pages-404-js-54074b9eed7af3fb3575.js","size":507}],"filteredAssets":0,"assetsSize":993492,"filteredAuxiliaryAssets":79,"auxiliaryAssetsSize":7191734},"component---src-pages-credits-js":{"name":"component---src-pages-credits-js","assets":[{"name":"styles.0f615b844f73f4ec7f93.css","size":57346},{"name":"c16184b3-019e6a7e87c7a4de7da9.js","size":8424},{"name":"2cca2479-62bb829e6f32669238be.js","size":3393},{"name":"b637e9a5-7c7096449bf2c50c0059.js","size":87228},{"name":"commons-8a6a7fb433791e1b3b36.js","size":836594},{"name":"component---src-pages-credits-js-927300b14458bd5f2fe2.js","size":3099}],"filteredAssets":0,"assetsSize":996084,"filteredAuxiliaryAssets":79,"auxiliaryAssetsSize":7195557},"component---src-pages-edit-page-js":{"name":"component---src-pages-edit-page-js","assets":[{"name":"styles.0f615b844f73f4ec7f93.css","size":57346},{"name":"c16184b3-019e6a7e87c7a4de7da9.js","size":8424},{"name":"2cca2479-62bb829e6f32669238be.js","size":3393},{"name":"b637e9a5-7c7096449bf2c50c0059.js","size":87228},{"name":"commons-8a6a7fb433791e1b3b36.js","size":836594},{"name":"component---src-pages-edit-page-js-4535f4aeced7ac394a65.js","size":4011}],"filteredAssets":0,"assetsSize":996996,"filteredAuxiliaryAssets":79,"auxiliaryAssetsSize":7204834},"component---src-pages-missing-info-js":{"name":"component---src-pages-missing-info-js","assets":[{"name":"styles.0f615b844f73f4ec7f93.css","size":57346},{"name":"c16184b3-019e6a7e87c7a4de7da9.js","size":8424},{"name":"2cca2479-62bb829e6f32669238be.js","size":3393},{"name":"b637e9a5-7c7096449bf2c50c0059.js","size":87228},{"name":"commons-8a6a7fb433791e1b3b36.js","size":836594},{"name":"8c5846ecd8d22969479b1d219d124d9383d2c4fd-616543129a83a6a84be4.js","size":49980},{"name":"47f1c355df703f1a34046e4573ab04dabc7ec99b-78d0f270853565081f98.js","size":17207},{"name":"component---src-pages-missing-info-js-ac14b56ca1560541d06e.js","size":9785}],"filteredAssets":0,"assetsSize":1069957,"filteredAuxiliaryAssets":81,"auxiliaryAssetsSize":7501490},"component---src-pages-profile-js":{"name":"component---src-pages-profile-js","assets":[{"name":"styles.0f615b844f73f4ec7f93.css","size":57346},{"name":"c16184b3-019e6a7e87c7a4de7da9.js","size":8424},{"name":"2cca2479-62bb829e6f32669238be.js","size":3393},{"name":"b637e9a5-7c7096449bf2c50c0059.js","size":87228},{"name":"commons-8a6a7fb433791e1b3b36.js","size":836594},{"name":"8c5846ecd8d22969479b1d219d124d9383d2c4fd-616543129a83a6a84be4.js","size":49980},{"name":"47f1c355df703f1a34046e4573ab04dabc7ec99b-78d0f270853565081f98.js","size":17207},{"name":"component---src-pages-profile-js-7fd8ccc64c853265a009.js","size":16747}],"filteredAssets":0,"assetsSize":1076919,"filteredAuxiliaryAssets":81,"auxiliaryAssetsSize":7530038},"component---src-pages-report-issue-js":{"name":"component---src-pages-report-issue-js","assets":[{"name":"styles.0f615b844f73f4ec7f93.css","size":57346},{"name":"c16184b3-019e6a7e87c7a4de7da9.js","size":8424},{"name":"2cca2479-62bb829e6f32669238be.js","size":3393},{"name":"b637e9a5-7c7096449bf2c50c0059.js","size":87228},{"name":"commons-8a6a7fb433791e1b3b36.js","size":836594},{"name":"component---src-pages-report-issue-js-99e6c03cc3ed8f326c63.js","size":3751}],"filteredAssets":0,"assetsSize":996736,"filteredAuxiliaryAssets":79,"auxiliaryAssetsSize":7203746},"component---src-pages-sign-in-js":{"name":"component---src-pages-sign-in-js","assets":[{"name":"styles.0f615b844f73f4ec7f93.css","size":57346},{"name":"c16184b3-019e6a7e87c7a4de7da9.js","size":8424},{"name":"2cca2479-62bb829e6f32669238be.js","size":3393},{"name":"b637e9a5-7c7096449bf2c50c0059.js","size":87228},{"name":"commons-8a6a7fb433791e1b3b36.js","size":836594},{"name":"8c5846ecd8d22969479b1d219d124d9383d2c4fd-616543129a83a6a84be4.js","size":49980},{"name":"component---src-pages-sign-in-js-2b25c2374458adaa61c7.js","size":3327}],"filteredAssets":0,"assetsSize":1046292,"filteredAuxiliaryAssets":80,"auxiliaryAssetsSize":7416684},"component---src-pages-sign-up-js":{"name":"component---src-pages-sign-up-js","assets":[{"name":"styles.0f615b844f73f4ec7f93.css","size":57346},{"name":"c16184b3-019e6a7e87c7a4de7da9.js","size":8424},{"name":"2cca2479-62bb829e6f32669238be.js","size":3393},{"name":"b637e9a5-7c7096449bf2c50c0059.js","size":87228},{"name":"commons-8a6a7fb433791e1b3b36.js","size":836594},{"name":"8c5846ecd8d22969479b1d219d124d9383d2c4fd-616543129a83a6a84be4.js","size":49980},{"name":"47f1c355df703f1a34046e4573ab04dabc7ec99b-78d0f270853565081f98.js","size":17207},{"name":"component---src-pages-sign-up-js-f1f4443e6d8185489009.js","size":15193}],"filteredAssets":0,"assetsSize":1075365,"filteredAuxiliaryAssets":82,"auxiliaryAssetsSize":7526527},"component---src-templates-course-content-template-js":{"name":"component---src-templates-course-content-template-js","assets":[{"name":"styles.0f615b844f73f4ec7f93.css","size":57346},{"name":"c16184b3-019e6a7e87c7a4de7da9.js","size":8424},{"name":"2cca2479-62bb829e6f32669238be.js","size":3393},{"name":"b637e9a5-7c7096449bf2c50c0059.js","size":87228},{"name":"e8647879-8bb9875b062ca21676fe.js","size":56720},{"name":"commons-8a6a7fb433791e1b3b36.js","size":836594},{"name":"8c5846ecd8d22969479b1d219d124d9383d2c4fd-616543129a83a6a84be4.js","size":49980},{"name":"47f1c355df703f1a34046e4573ab04dabc7ec99b-78d0f270853565081f98.js","size":17207},{"name":"5c90745c52677d2b7909323d086ca518b9bc7e92-d96b526d04f1458de1c1.js","size":717136},{"name":"component---src-templates-course-content-template-js-e06e0e976f3d344acdaa.js","size":4538}],"filteredAssets":0,"assetsSize":1838566,"filteredAuxiliaryAssets":83,"auxiliaryAssetsSize":10136279},"component---src-templates-course-part-overview-template-js":{"name":"component---src-templates-course-part-overview-template-js","assets":[{"name":"styles.0f615b844f73f4ec7f93.css","size":57346},{"name":"c16184b3-019e6a7e87c7a4de7da9.js","size":8424},{"name":"2cca2479-62bb829e6f32669238be.js","size":3393},{"name":"b637e9a5-7c7096449bf2c50c0059.js","size":87228},{"name":"e8647879-8bb9875b062ca21676fe.js","size":56720},{"name":"commons-8a6a7fb433791e1b3b36.js","size":836594},{"name":"8c5846ecd8d22969479b1d219d124d9383d2c4fd-616543129a83a6a84be4.js","size":49980},{"name":"47f1c355df703f1a34046e4573ab04dabc7ec99b-78d0f270853565081f98.js","size":17207},{"name":"5c90745c52677d2b7909323d086ca518b9bc7e92-d96b526d04f1458de1c1.js","size":717136},{"name":"component---src-templates-course-part-overview-template-js-e2dfb9066039dade764a.js","size":1673}],"filteredAssets":0,"assetsSize":1835701,"filteredAuxiliaryAssets":83,"auxiliaryAssetsSize":10127476},"component---src-templates-info-page-template-js":{"name":"component---src-templates-info-page-template-js","assets":[{"name":"styles.0f615b844f73f4ec7f93.css","size":57346},{"name":"c16184b3-019e6a7e87c7a4de7da9.js","size":8424},{"name":"2cca2479-62bb829e6f32669238be.js","size":3393},{"name":"b637e9a5-7c7096449bf2c50c0059.js","size":87228},{"name":"e8647879-8bb9875b062ca21676fe.js","size":56720},{"name":"commons-8a6a7fb433791e1b3b36.js","size":836594},{"name":"8c5846ecd8d22969479b1d219d124d9383d2c4fd-616543129a83a6a84be4.js","size":49980},{"name":"47f1c355df703f1a34046e4573ab04dabc7ec99b-78d0f270853565081f98.js","size":17207},{"name":"5c90745c52677d2b7909323d086ca518b9bc7e92-d96b526d04f1458de1c1.js","size":717136},{"name":"component---src-templates-info-page-template-js-f1111198e1e4d7d5357e.js","size":2505}],"filteredAssets":0,"assetsSize":1836533,"filteredAuxiliaryAssets":83,"auxiliaryAssetsSize":10128222},"component---src-templates-vocabulary-template-js":{"name":"component---src-templates-vocabulary-template-js","assets":[{"name":"styles.0f615b844f73f4ec7f93.css","size":57346},{"name":"c16184b3-019e6a7e87c7a4de7da9.js","size":8424},{"name":"2cca2479-62bb829e6f32669238be.js","size":3393},{"name":"b637e9a5-7c7096449bf2c50c0059.js","size":87228},{"name":"e8647879-8bb9875b062ca21676fe.js","size":56720},{"name":"commons-8a6a7fb433791e1b3b36.js","size":836594},{"name":"8c5846ecd8d22969479b1d219d124d9383d2c4fd-616543129a83a6a84be4.js","size":49980},{"name":"47f1c355df703f1a34046e4573ab04dabc7ec99b-78d0f270853565081f98.js","size":17207},{"name":"5c90745c52677d2b7909323d086ca518b9bc7e92-d96b526d04f1458de1c1.js","size":717136},{"name":"component---src-templates-vocabulary-template-js-87598608c80c5f8b70c1.js","size":1435}],"filteredAssets":0,"assetsSize":1835463,"filteredAuxiliaryAssets":83,"auxiliaryAssetsSize":10126918}},"assetsByChunkName":{"polyfill":["webpack-runtime-d883e5a693f658cfd86d.js","commons-8a6a7fb433791e1b3b36.js","polyfill-b792846b84be83ff28ed.js"],"app":["webpack-runtime-d883e5a693f658cfd86d.js","styles.0f615b844f73f4ec7f93.css","framework-3a2d1079ef1a8666f37a.js","app-6555c2e857f6df37dde5.js"],"component---src-pages-404-js":["styles.0f615b844f73f4ec7f93.css","c16184b3-019e6a7e87c7a4de7da9.js","2cca2479-62bb829e6f32669238be.js","b637e9a5-7c7096449bf2c50c0059.js","commons-8a6a7fb433791e1b3b36.js","component---src-pages-404-js-54074b9eed7af3fb3575.js"],"component---src-pages-credits-js":["styles.0f615b844f73f4ec7f93.css","c16184b3-019e6a7e87c7a4de7da9.js","2cca2479-62bb829e6f32669238be.js","b637e9a5-7c7096449bf2c50c0059.js","commons-8a6a7fb433791e1b3b36.js","component---src-pages-credits-js-927300b14458bd5f2fe2.js"],"component---src-pages-edit-page-js":["styles.0f615b844f73f4ec7f93.css","c16184b3-019e6a7e87c7a4de7da9.js","2cca2479-62bb829e6f32669238be.js","b637e9a5-7c7096449bf2c50c0059.js","commons-8a6a7fb433791e1b3b36.js","component---src-pages-edit-page-js-4535f4aeced7ac394a65.js"],"component---src-pages-missing-info-js":["styles.0f615b844f73f4ec7f93.css","c16184b3-019e6a7e87c7a4de7da9.js","2cca2479-62bb829e6f32669238be.js","b637e9a5-7c7096449bf2c50c0059.js","commons-8a6a7fb433791e1b3b36.js","8c5846ecd8d22969479b1d219d124d9383d2c4fd-616543129a83a6a84be4.js","47f1c355df703f1a34046e4573ab04dabc7ec99b-78d0f270853565081f98.js","component---src-pages-missing-info-js-ac14b56ca1560541d06e.js"],"component---src-pages-profile-js":["styles.0f615b844f73f4ec7f93.css","c16184b3-019e6a7e87c7a4de7da9.js","2cca2479-62bb829e6f32669238be.js","b637e9a5-7c7096449bf2c50c0059.js","commons-8a6a7fb433791e1b3b36.js","8c5846ecd8d22969479b1d219d124d9383d2c4fd-616543129a83a6a84be4.js","47f1c355df703f1a34046e4573ab04dabc7ec99b-78d0f270853565081f98.js","component---src-pages-profile-js-7fd8ccc64c853265a009.js"],"component---src-pages-report-issue-js":["styles.0f615b844f73f4ec7f93.css","c16184b3-019e6a7e87c7a4de7da9.js","2cca2479-62bb829e6f32669238be.js","b637e9a5-7c7096449bf2c50c0059.js","commons-8a6a7fb433791e1b3b36.js","component---src-pages-report-issue-js-99e6c03cc3ed8f326c63.js"],"component---src-pages-sign-in-js":["styles.0f615b844f73f4ec7f93.css","c16184b3-019e6a7e87c7a4de7da9.js","2cca2479-62bb829e6f32669238be.js","b637e9a5-7c7096449bf2c50c0059.js","commons-8a6a7fb433791e1b3b36.js","8c5846ecd8d22969479b1d219d124d9383d2c4fd-616543129a83a6a84be4.js","component---src-pages-sign-in-js-2b25c2374458adaa61c7.js"],"component---src-pages-sign-up-js":["styles.0f615b844f73f4ec7f93.css","c16184b3-019e6a7e87c7a4de7da9.js","2cca2479-62bb829e6f32669238be.js","b637e9a5-7c7096449bf2c50c0059.js","commons-8a6a7fb433791e1b3b36.js","8c5846ecd8d22969479b1d219d124d9383d2c4fd-616543129a83a6a84be4.js","47f1c355df703f1a34046e4573ab04dabc7ec99b-78d0f270853565081f98.js","component---src-pages-sign-up-js-f1f4443e6d8185489009.js"],"component---src-templates-course-content-template-js":["styles.0f615b844f73f4ec7f93.css","c16184b3-019e6a7e87c7a4de7da9.js","2cca2479-62bb829e6f32669238be.js","b637e9a5-7c7096449bf2c50c0059.js","e8647879-8bb9875b062ca21676fe.js","commons-8a6a7fb433791e1b3b36.js","8c5846ecd8d22969479b1d219d124d9383d2c4fd-616543129a83a6a84be4.js","47f1c355df703f1a34046e4573ab04dabc7ec99b-78d0f270853565081f98.js","5c90745c52677d2b7909323d086ca518b9bc7e92-d96b526d04f1458de1c1.js","component---src-templates-course-content-template-js-e06e0e976f3d344acdaa.js"],"component---src-templates-course-part-overview-template-js":["styles.0f615b844f73f4ec7f93.css","c16184b3-019e6a7e87c7a4de7da9.js","2cca2479-62bb829e6f32669238be.js","b637e9a5-7c7096449bf2c50c0059.js","e8647879-8bb9875b062ca21676fe.js","commons-8a6a7fb433791e1b3b36.js","8c5846ecd8d22969479b1d219d124d9383d2c4fd-616543129a83a6a84be4.js","47f1c355df703f1a34046e4573ab04dabc7ec99b-78d0f270853565081f98.js","5c90745c52677d2b7909323d086ca518b9bc7e92-d96b526d04f1458de1c1.js","component---src-templates-course-part-overview-template-js-e2dfb9066039dade764a.js"],"component---src-templates-info-page-template-js":["styles.0f615b844f73f4ec7f93.css","c16184b3-019e6a7e87c7a4de7da9.js","2cca2479-62bb829e6f32669238be.js","b637e9a5-7c7096449bf2c50c0059.js","e8647879-8bb9875b062ca21676fe.js","commons-8a6a7fb433791e1b3b36.js","8c5846ecd8d22969479b1d219d124d9383d2c4fd-616543129a83a6a84be4.js","47f1c355df703f1a34046e4573ab04dabc7ec99b-78d0f270853565081f98.js","5c90745c52677d2b7909323d086ca518b9bc7e92-d96b526d04f1458de1c1.js","component---src-templates-info-page-template-js-f1111198e1e4d7d5357e.js"],"component---src-templates-vocabulary-template-js":["styles.0f615b844f73f4ec7f93.css","c16184b3-019e6a7e87c7a4de7da9.js","2cca2479-62bb829e6f32669238be.js","b637e9a5-7c7096449bf2c50c0059.js","e8647879-8bb9875b062ca21676fe.js","commons-8a6a7fb433791e1b3b36.js","8c5846ecd8d22969479b1d219d124d9383d2c4fd-616543129a83a6a84be4.js","47f1c355df703f1a34046e4573ab04dabc7ec99b-78d0f270853565081f98.js","5c90745c52677d2b7909323d086ca518b9bc7e92-d96b526d04f1458de1c1.js","component---src-templates-vocabulary-template-js-87598608c80c5f8b70c1.js"]},"childAssetsByChunkName":{}}